awadeuwu1234/__init__.py
awadeuwu1234/pokemon.csv
awadeuwu1234/random_pokemon.py
awadeuwu1234-1.0.0.dist-info/METADATA
awadeuwu1234-1.0.0.dist-info/WHEEL
awadeuwu1234-1.0.0.dist-info/top_level.txt
awadeuwu1234-1.0.0.dist-info/RECORD
